completion_aggregator/__init__.py
completion_aggregator/admin.py
completion_aggregator/apps.py
completion_aggregator/batch.py
completion_aggregator/cachegroup.py
completion_aggregator/compat.py
completion_aggregator/core.py
completion_aggregator/models.py
completion_aggregator/serializers.py
completion_aggregator/signals.py
completion_aggregator/transformers.py
completion_aggregator/urls.py
completion_aggregator/utils.py
completion_aggregator/views.py
completion_aggregator/xapi.py
completion_aggregator/api/__init__.py
completion_aggregator/api/common.py
completion_aggregator/api/v0/__init__.py
completion_aggregator/api/v0/urls.py
completion_aggregator/api/v0/views.py
completion_aggregator/api/v1/__init__.py
completion_aggregator/api/v1/urls.py
completion_aggregator/api/v1/views.py
completion_aggregator/management/__init__.py
completion_aggregator/management/commands/__init__.py
completion_aggregator/management/commands/migrate_progress.py
completion_aggregator/management/commands/reaggregate_course.py
completion_aggregator/management/commands/run_aggregator_cleanup.py
completion_aggregator/management/commands/run_aggregator_service.py
completion_aggregator/management/commands/run_aggregator_test.py
completion_aggregator/migrations/0001_initial.py
completion_aggregator/migrations/0002_aggregator_last_modified.py
completion_aggregator/migrations/0003_stalecompletion.py
completion_aggregator/migrations/0004_index_stalecompletion.py
completion_aggregator/migrations/0005_cachegroupinvalidation.py
completion_aggregator/migrations/__init__.py
completion_aggregator/settings/__init__.py
completion_aggregator/settings/aws.py
completion_aggregator/settings/common.py
completion_aggregator/tasks/__init__.py
completion_aggregator/tasks/aggregation_tasks.py
completion_aggregator/tasks/handler_tasks.py
completion_aggregator/templates/chapter_completion_progress_bar.html
completion_aggregator/templates/completion_progress_bar.html
openedx_completion_aggregator-4.2.0.dist-info/AUTHORS
openedx_completion_aggregator-4.2.0.dist-info/LICENSE.txt
openedx_completion_aggregator-4.2.0.dist-info/METADATA
openedx_completion_aggregator-4.2.0.dist-info/WHEEL
openedx_completion_aggregator-4.2.0.dist-info/entry_points.txt
openedx_completion_aggregator-4.2.0.dist-info/top_level.txt
openedx_completion_aggregator-4.2.0.dist-info/RECORD
