Metadata-Version: 2.1
Name: openedx-completion-aggregator
Version: 4.2.0
Summary: an app that aggregates block level completion data for different block types for Open edX.
Home-page: https://github.com/open-craft/openedx-completion-aggregator
Author: OpenCraft
Author-email: help@opencraft.com
License: AGPL 3.0
Keywords: Django edx
Classifier: Development Status :: 3 - Alpha
Classifier: Framework :: Django
Classifier: Framework :: Django :: 3.2
Classifier: Intended Audience :: Developers
Classifier: License :: OSI Approved :: GNU Affero General Public License v3 or later (AGPLv3+)
Classifier: Natural Language :: English
Classifier: Programming Language :: Python :: 3.8
License-File: LICENSE.txt
License-File: AUTHORS
Requires-Dist: Django
Requires-Dist: XBlock
Requires-Dist: celery
Requires-Dist: django-model-utils
Requires-Dist: djangorestframework
Requires-Dist: edx-celeryutils
Requires-Dist: edx-completion
Requires-Dist: edx-event-routing-backends
Requires-Dist: edx-opaque-keys
Requires-Dist: edx-toggles
Requires-Dist: event-tracking
Requires-Dist: six
